_nx_parallel/__init__.py
_nx_parallel/config.py
_nx_parallel/update_get_info.py
nx_parallel/__init__.py
nx_parallel/interface.py
nx_parallel/algorithms/__init__.py
nx_parallel/algorithms/cluster.py
nx_parallel/algorithms/dag.py
nx_parallel/algorithms/efficiency_measures.py
nx_parallel/algorithms/isolate.py
nx_parallel/algorithms/link_prediction.py
nx_parallel/algorithms/tournament.py
nx_parallel/algorithms/vitality.py
nx_parallel/algorithms/approximation/__init__.py
nx_parallel/algorithms/approximation/connectivity.py
nx_parallel/algorithms/assortativity/__init__.py
nx_parallel/algorithms/assortativity/neighbor_degree.py
nx_parallel/algorithms/bipartite/__init__.py
nx_parallel/algorithms/bipartite/redundancy.py
nx_parallel/algorithms/centrality/__init__.py
nx_parallel/algorithms/centrality/betweenness.py
nx_parallel/algorithms/centrality/harmonic.py
nx_parallel/algorithms/components/__init__.py
nx_parallel/algorithms/components/attracting.py
nx_parallel/algorithms/components/connected.py
nx_parallel/algorithms/components/strongly_connected.py
nx_parallel/algorithms/components/weakly_connected.py
nx_parallel/algorithms/connectivity/__init__.py
nx_parallel/algorithms/connectivity/connectivity.py
nx_parallel/algorithms/shortest_paths/__init__.py
nx_parallel/algorithms/shortest_paths/generic.py
nx_parallel/algorithms/shortest_paths/unweighted.py
nx_parallel/algorithms/shortest_paths/weighted.py
nx_parallel/utils/__init__.py
nx_parallel/utils/chunk.py
nx_parallel/utils/decorators.py
nx_parallel/utils/should_run_policies.py
nx_parallel-0.4.dist-info/licenses/LICENSE.md
nx_parallel-0.4.dist-info/METADATA
nx_parallel-0.4.dist-info/WHEEL
nx_parallel-0.4.dist-info/entry_points.txt
nx_parallel-0.4.dist-info/top_level.txt
nx_parallel-0.4.dist-info/RECORD
