Metadata-Version: 2.4
Name: nx-parallel
Version: 0.4
Summary: A parallel backend for NetworkX. It uses joblib to run NetworkX algorithms on multiple CPU cores.
Author-email: NetworkX Devs <networkx-core@discuss.scientific-python.org>
Maintainer-email: NetworkX Developers <networkx-discuss@googlegroups.com>
License: BSD-3-Clause
Project-URL: Bug Tracker, https://github.com/networkx/nx-parallel/issues
Project-URL: Source Code, https://github.com/networkx/nx-parallel
Keywords: networkx,graphs,algorithms,parallel
Platform: Linux
Platform: Mac OSX
Platform: Windows
Platform: Unix
Classifier: Intended Audience :: Developers
Classifier: Intended Audience :: Science/Research
Classifier: License :: OSI Approved :: BSD License
Classifier: Operating System :: OS Independent
Classifier: Programming Language :: Python :: 3
Classifier: Programming Language :: Python :: 3.12
Classifier: Programming Language :: Python :: 3.13
Classifier: Programming Language :: Python :: 3.14
Classifier: Programming Language :: Python :: 3 :: Only
Requires-Python: >=3.12
License-File: LICENSE.md
Requires-Dist: networkx>=3.4.2
Requires-Dist: joblib>=1.5.0
Provides-Extra: developer
Requires-Dist: pre-commit; extra == "developer"
Requires-Dist: ruff==0.14.0; extra == "developer"
Provides-Extra: heatmap
Requires-Dist: matplotlib>=3.9; extra == "heatmap"
Requires-Dist: seaborn>=0.13.2; extra == "heatmap"
Requires-Dist: pandas>=2.2; extra == "heatmap"
Provides-Extra: test
Requires-Dist: pytest>=7.2; extra == "test"
Requires-Dist: numpy>=2; extra == "test"
Requires-Dist: scipy>=1.12; extra == "test"
Dynamic: license-file
